psychicapi/__init__.py
psychicapi/psychic.py
psychicapi-0.8.4.dist-info/METADATA
psychicapi-0.8.4.dist-info/WHEEL
psychicapi-0.8.4.dist-info/top_level.txt
psychicapi-0.8.4.dist-info/RECORD
