Metadata-Version: 2.1
Name: psychicapi
Version: 0.8.4
Summary: Psychic.dev is an open-source data integration platform for LLMs. This is the Python client for Psychic
Author: Ayan Bandyopadhyay
Author-email: ayan@psychic.dev
